mycgi.py
mycgi-0.0.10.dist-info/METADATA
mycgi-0.0.10.dist-info/WHEEL
mycgi-0.0.10.dist-info/top_level.txt
mycgi-0.0.10.dist-info/RECORD
