Metadata-Version: 2.4
Name: mycgi
Version: 0.0.10
Summary: A Python3 replacement for the deprecated cgi module
Author-email: Ronald Aaronson <ronaldaaronson@gmail.com>
License: Apache-2.0
Project-URL: Homepage, https://github.com/ronaaronson/mycgi
Project-URL: Changelog, https://github.com/ronaaronson/mycgi/tags
Project-URL: Source, https://github.com/ronaaronson/mycgi
Keywords: cgi,replacement
Classifier: License :: OSI Approved :: Apache Software License
Classifier: Programming Language :: Python :: 3
Requires-Python: >=3.8
Requires-Dist: python-multipart>=0.0.20
